input_timeout/LICENSE
input_timeout/README.MD
input_timeout/__init__.py
input_timeout/requirements.txt
input_timeout/thirdparty.json
input_timeout-0.21.dist-info/LICENSE.rst
input_timeout-0.21.dist-info/METADATA
input_timeout-0.21.dist-info/WHEEL
input_timeout-0.21.dist-info/top_level.txt
input_timeout-0.21.dist-info/RECORD
