Metadata-Version: 2.1
Name: input_timeout
Version: 0.21
Summary: Like python's input(), but with timeout and default value
Home-page: https://github.com/hansalemaos/input_timeout
Author: Johannes Fischer
Author-email: <aulasparticularesdealemaosp@gmail.com>
License: MIT
Keywords: timeout,input,default,value
Classifier: Development Status :: 4 - Beta
Classifier: Programming Language :: Python :: 3 :: Only
Classifier: Programming Language :: Python :: 3.9
Classifier: Topic :: Scientific/Engineering :: Visualization
Classifier: Topic :: Software Development :: Libraries :: Python Modules
Classifier: Topic :: Text Editors :: Text Processing
Classifier: Topic :: Text Processing :: General
Classifier: Topic :: Text Processing :: Indexing
Classifier: Topic :: Text Processing :: Filters
Classifier: Topic :: Utilities
License-File: LICENSE.rst
